antsxmm/__init__.py
antsxmm/_version.py
antsxmm/bids.py
antsxmm/core.py
antsxmm/pipeline.py
antsxmm-1.1.1.dev0.dist-info/METADATA
antsxmm-1.1.1.dev0.dist-info/WHEEL
antsxmm-1.1.1.dev0.dist-info/entry_points.txt
antsxmm-1.1.1.dev0.dist-info/top_level.txt
antsxmm-1.1.1.dev0.dist-info/RECORD
