Metadata-Version: 2.4
Name: antsxmm
Version: 1.1.1.dev0
Summary: A streamlined wrapper for ANTsPyMM tailored for antsxbids BIDS output
Author: ANTsX Community
Requires-Python: >=3.9
Requires-Dist: antspymm>=1.1.0
Requires-Dist: antspyt1w
Requires-Dist: pandas>=1.0.0
Requires-Dist: tqdm
Requires-Dist: click
Requires-Dist: antspyx
Requires-Dist: importlib-metadata; python_version < "3.8"
Provides-Extra: test
Requires-Dist: pytest; extra == "test"
Requires-Dist: pytest-cov; extra == "test"
Requires-Dist: pytest-mock; extra == "test"
